pytoil/__init__.py
pytoil/__main__.py
pytoil/exceptions.py
pytoil/py.typed
pytoil/api/__init__.py
pytoil/api/api.py
pytoil/api/queries.py
pytoil/cli/__init__.py
pytoil/cli/bug.py
pytoil/cli/checkout.py
pytoil/cli/config.py
pytoil/cli/docs.py
pytoil/cli/find.py
pytoil/cli/gh.py
pytoil/cli/info.py
pytoil/cli/keep.py
pytoil/cli/new.py
pytoil/cli/printer.py
pytoil/cli/pull.py
pytoil/cli/remove.py
pytoil/cli/root.py
pytoil/cli/show.py
pytoil/cli/utils.py
pytoil/config/__init__.py
pytoil/config/config.py
pytoil/config/defaults.py
pytoil/editor/__init__.py
pytoil/editor/editor.py
pytoil/environments/__init__.py
pytoil/environments/base.py
pytoil/environments/conda.py
pytoil/environments/flit.py
pytoil/environments/poetry.py
pytoil/environments/reqs.py
pytoil/environments/virtualenv.py
pytoil/git/__init__.py
pytoil/git/git.py
pytoil/repo/__init__.py
pytoil/repo/repo.py
pytoil/starters/__init__.py
pytoil/starters/base.py
pytoil/starters/go.py
pytoil/starters/python.py
pytoil/starters/rust.py
pytoil-0.41.0.dist-info/METADATA
pytoil-0.41.0.dist-info/WHEEL
pytoil-0.41.0.dist-info/entry_points.txt
pytoil-0.41.0.dist-info/licenses/LICENSE
pytoil-0.41.0.dist-info/RECORD
