Metadata-Version: 2.3
Name: pytoil
Version: 0.41.0
Summary: CLI to automate the development workflow.
Project-URL: Documentation, https://FollowTheProcess.github.io/pytoil/
Project-URL: Homepage, https://github.com/FollowTheProcess/pytoil
Project-URL: Source, https://github.com/FollowTheProcess/pytoil
Author: Tom Fleet
Author-email: tomfleet2018@gmail.com
Maintainer: Tom Fleet
Maintainer-email: tomfleet2018@gmail.com
License: Apache Software License 2.0
License-File: LICENSE
Keywords: automation,cli,developer-tools,python
Classifier: Development Status :: 3 - Alpha
Classifier: Environment :: Console
Classifier: Intended Audience :: Developers
Classifier: License :: OSI Approved :: Apache Software License
Classifier: Natural Language :: English
Classifier: Operating System :: MacOS :: MacOS X
Classifier: Operating System :: Microsoft :: Windows
Classifier: Operating System :: OS Independent
Classifier: Operating System :: POSIX :: Linux
Classifier: Programming Language :: Python :: 3 :: Only
Classifier: Programming Language :: Python :: 3.9
Classifier: Programming Language :: Python :: 3.10
Classifier: Programming Language :: Python :: 3.11
Classifier: Programming Language :: Python :: 3.12
Classifier: Topic :: Software Development
Classifier: Topic :: Utilities
Classifier: Typing :: Typed
Requires-Python: >=3.9
Requires-Dist: click==8.1.7
Requires-Dist: cookiecutter==2.6
Requires-Dist: copier==9.3.1
Requires-Dist: httpx==0.27
Requires-Dist: humanize==4.10
Requires-Dist: pydantic==2.8.2
Requires-Dist: pyyaml==6.0.2
Requires-Dist: questionary==2.0.1
Requires-Dist: rich==13.7.1
Requires-Dist: rtoml==0.11
Requires-Dist: thefuzz[speedup]==0.22.1
Requires-Dist: virtualenv==20.26.3
